pytest_whirlwind/__init__.py
pytest_whirlwind-0.1.0.dist-info/entry_points.txt
pytest_whirlwind-0.1.0.dist-info/LICENSE
pytest_whirlwind-0.1.0.dist-info/WHEEL
pytest_whirlwind-0.1.0.dist-info/METADATA
pytest_whirlwind-0.1.0.dist-info/RECORD
