Metadata-Version: 2.1
Name: pytest-whirlwind
Version: 0.1.0
Summary: Testing Tornado.
Home-page: https://github.com/supakeen/pytest-whirlwind
License: MIT
Keywords: tornado,pytest
Author: supakeen
Author-email: cmdr@supakeen.com
Requires-Python: >=3.6,<4
Classifier: License :: OSI Approved :: MIT License
Classifier: Programming Language :: Python
Classifier: Programming Language :: Python :: 3
Classifier: Programming Language :: Python :: 3.6
Classifier: Programming Language :: Python :: 3.7
Classifier: Programming Language :: Python :: 3.8
Requires-Dist: tornado (>=6.0.4,<7.0.0)
Project-URL: Repository, https://github.com/supakeen/pytest-whirlwind
